pdm_template-0.1.8.dist-info/METADATA
pdm_template-0.1.8.dist-info/WHEEL
pdm_template-0.1.8.dist-info/entry_points.txt
pdm_template/__init__.py
pdm_template/check_changelog.py
pdm_template/extract_todo.py
pdm_template/fix_doc.py
pdm_template/resource/script/bootstrap.bundle.min.js
pdm_template/resource/script/highlight.min.js
pdm_template/resource/script/latest.js
pdm_template/resource/script/list.min.js
pdm_template/resource/style/bootstrap.min.css
pdm_template/resource/style/github.min.css
pdm_template/resource/style/normalize.min.css
pdm_template/resource/style/sanitize.min.css
pdm_template/resource/style/typography.min.css
pdm_template-0.1.8.dist-info/RECORD
